{
  "problem_id": "CF1109C",
  "source": "codeforces",
  "dimension": "invariant",
  "round": 1,
  "result": {
    "invariants": [
      {
        "name": "monotonicity",
        "description": "时间轴上的事件处理顺序单调递增，确保事件按时间顺序处理",
        "properties": {
          "left_monotonic": false,
          "right_monotonic": true
        }
      },
      {
        "name": "interval_additivity",
        "description": "在指定的时间区间内，耐心的变化量可以通过区间端点的差值计算得出",
        "properties": {}
      },
      {
        "name": "state_transition",
        "description": "系统状态（当前耐心量）根据事件的发生进行一致性的转移",
        "properties": {}
      }
    ]
  },
  "status": "success"
}