{
  "problem_id": "CF156C",
  "source": "codeforces",
  "dimension": "invariant",
  "round": 1,
  "result": {
    "invariants": [
      {
        "name": "optimal_substructure",
        "description": "最优子结构：问题的解可以通过子问题的解来构建，且子问题的解是独立的。",
        "properties": {
          "subproblem_independence": true
        }
      },
      {
        "name": "state_transition",
        "description": "状态转移不变量：通过定义状态和状态转移方程，确保从一个状态到另一个状态的转换是合法且一致的。",
        "properties": {}
      },
      {
        "name": "modular_arithmetic",
        "description": "模运算不变量：在计算过程中，所有中间结果和最终结果都对给定的模数取模，以防止数值溢出。",
        "properties": {
          "modulus": 1000000007
        }
      }
    ]
  },
  "status": "success"
}