{
  "problem_id": "CF1556E",
  "source": "codeforces",
  "dimension": "core_constraints",
  "round": 1,
  "result": {
    "constraints": [
      {
        "name": "pairwise_difference",
        "description": "数组 a 和 b 在每个位置的差值必须能够通过一系列操作变为 0，且每次操作选择的索引数量为偶数",
        "formal": "对于每个 i ∈ [l, r]，存在一系列操作使得 a_i - b_i = 0，且每次操作选择的索引数量为偶数"
      },
      {
        "name": "operation_limit",
        "description": "每次操作必须选择偶数个索引，并且这些索引必须是递增的",
        "formal": "每次操作选择的索引 pos_1, pos_2, ..., pos_k 满足 l ≤ pos_1 < pos_2 < ... < pos_k ≤ r 且 k 为偶数"
      },
      {
        "name": "adjacency_relation",
        "description": "每次操作中，a 数组在奇数位置的元素加 1，b 数组在偶数位置的元素加 1",
        "formal": "对于每次操作，a[pos_1], a[pos_3], ... 加 1；b[pos_2], b[pos_4], ... 加 1"
      }
    ]
  },
  "status": "success"
}