{
  "problem_id": "CF1734E",
  "source": "codeforces",
  "dimension": "core_constraints",
  "round": 1,
  "result": {
    "constraints": [
      {
        "name": "distinctness",
        "description": "矩阵的每一行和每一列中的元素必须互不相同（即每行和每列都是一个排列）",
        "formal": "∀i, j, k (1 ≤ i, j, k ≤ n), a[i][k] ≢ a[j][k] (mod n) 且 a[k][i] ≢ a[k][j] (mod n)"
      },
      {
        "name": "diagonal_constraint",
        "description": "矩阵的主对角线上的元素必须等于给定数组 b 中的对应元素",
        "formal": "∀i (1 ≤ i ≤ n), a[i][i] = b[i]"
      }
    ]
  },
  "status": "success"
}