{
  "problem_id": "P10846",
  "source": "luogu",
  "dimension": "core_constraints",
  "round": 1,
  "result": {
    "constraints": [
      {
        "name": "tree_structure",
        "description": "层级结构为一棵树，根节点为0，每个节点有唯一的父节点"
      },
      {
        "name": "language_preference",
        "description": "每个节点有一个首选编程语言，且每种语言的员工数量有限"
      },
      {
        "name": "same_level_exchange",
        "description": "只能交换同一层级的两个节点，其中一个在子树中且语言不同，另一个不在子树中但语言相同"
      },
      {
        "name": "maximize_participants",
        "description": "目标是最大化参与项目的员工数量，并且最小化调换次数"
      }
    ]
  },
  "status": "success"
}