{
  "problem_id": "P12336",
  "source": "luogu",
  "dimension": "invariant",
  "round": 1,
  "result": {
    "invariants": [
      {
        "name": "optimal_substructure",
        "description": "最优解包含子问题的最优解，通过构造满足条件的四元组 (a, b, c, d) 时，可以将问题分解为更小的子问题来解决。",
        "properties": {}
      },
      {
        "name": "greedy_choice",
        "description": "局部最优选择导致全局最优，通过选择合适的 b, c, d 使得 sqrt(a^2 + b^2 + c^2 + d^2) = a ⊕ b ⊕ c ⊕ d 成立。",
        "properties": {}
      }
    ]
  },
  "status": "success"
}