{
  "problem_id": "P3571",
  "source": "luogu",
  "dimension": "invariant",
  "round": 1,
  "result": {
    "invariants": [
      {
        "name": "optimal_substructure",
        "description": "最优子结构：每个节点的最小执行时间依赖于其子节点的最小执行时间，满足树形DP的最优子结构性质",
        "properties": {}
      },
      {
        "name": "divide_conquer",
        "description": "分治不变量：大问题的解可以通过子问题的解合成，具体表现为树的根节点的最小执行时间由其所有子树的最小执行时间决定",
        "properties": {}
      },
      {
        "name": "state_transition",
        "description": "状态转移不变量：在处理每个节点时，其状态（即最小执行时间）通过其子节点的状态进行转移，并且这种转移是确定性的",
        "properties": {}
      }
    ]
  },
  "status": "success"
}