{
  "problem_id": "P7163",
  "source": "luogu",
  "dimension": "invariant",
  "round": 1,
  "result": {
    "invariants": [
      {
        "name": "state_transition",
        "description": "状态转移不变量：通过改变灯泡的状态，可以逐步将所有灯泡变为打开状态。每次操作只影响当前灯泡及其相邻灯泡的状态。",
        "properties": {}
      },
      {
        "name": "optimal_substructure",
        "description": "最优子结构：整个问题的最优解可以通过子树的最优解组合得到。每个子树的最优解是独立且可合并的。",
        "properties": {}
      },
      {
        "name": "greedy_choice",
        "description": "贪心选择性质：每次选择一个序列中的灯泡进行操作，使得当前局部最优解能够逐步逼近全局最优解。",
        "properties": {}
      }
    ]
  },
  "status": "success"
}