{
  "problem_id": "P7322",
  "source": "luogu",
  "dimension": "core_constraints",
  "round": 1,
  "result": {
    "constraints": [
      {
        "name": "permutation_constraint",
        "description": "输入是一个长度为 n 的排列，即每个在 [1, n] 中的整数都在排列中恰好出现一次"
      },
      {
        "name": "subsequence_constraint",
        "description": "定义 f(a) 为 a 的 k 长度滑动窗口的最大值序列",
        "formal": "f(a) = {max_{i=1}^{k}{a_i}, max_{i=2}^{k+1}{a_i}, ..., max_{i=n-k+1}^{n}{a_i}}"
      },
      {
        "name": "distinctness",
        "description": "w(a) 定义为 a 中不同元素的数量",
        "formal": "w(a) = |{a_i | i ∈ [1, n]}|"
      }
    ]
  },
  "status": "success"
}