{
  "problem_id": "P8866",
  "source": "luogu",
  "dimension": "invariant",
  "round": 1,
  "result": {
    "invariants": [
      {
        "name": "state_transition",
        "description": "状态转移不变量：每一步操作后，系统状态（牌堆和栈的状态）的合法性保持不变，且逐步向目标状态（所有卡牌消去）推进。",
        "properties": {}
      },
      {
        "name": "optimal_substructure",
        "description": "最优子结构：整个问题的解可以通过解决一系列子问题（即每一步的操作）来构建，每个子问题的解都是局部最优的。",
        "properties": {}
      },
      {
        "name": "symmetry",
        "description": "对称性：对于任意两个具有相同图案的卡牌，无论它们在哪个栈中，都可以通过操作将其消去，从而消除个体差异。",
        "properties": {}
      }
    ]
  },
  "status": "success"
}