{
  "problem_id": "P9368",
  "source": "luogu",
  "dimension": "invariant",
  "round": 1,
  "result": {
    "invariants": [
      {
        "name": "monotonicity",
        "description": "双指针左右端点单调前进，通过调整指针位置来维护矩形的合法性",
        "properties": {
          "left_monotonic": true,
          "right_monotonic": true
        }
      },
      {
        "name": "optimal_substructure",
        "description": "最优解包含子问题的最优解，即最大面积的矩形可以通过子矩形的最优解组合得到",
        "properties": {}
      },
      {
        "name": "interval_additivity",
        "description": "区间可加性，矩形的成本可以通过其边长和权重的乘积累加计算",
        "properties": {}
      }
    ]
  },
  "status": "success"
}