{
  "problem_id": "P11455",
  "source": "luogu",
  "dimension": "core_constraints",
  "round": 3,
  "result": {
    "constraints": [
      {
        "name": "same_label_within_x",
        "description": "如果一些奶牛具有相同的标号，并且他们两两之间的距离都在 x 头牛以内，那么这些奶牛可以组成一个友谊小组。",
        "formal": "对于所有 i, j (1 ≤ i < j ≤ N)，如果 a[i] = a[j] 且 j - i ≤ x，则奶牛 i 和 j 可以在同一个友谊小组。"
      },
      {
        "name": "each_cow_in_one_group",
        "description": "每头奶牛必须恰好属于一个友谊小组。",
        "formal": "对于每个 i (1 ≤ i ≤ N)，存在唯一的友谊小组 G 使得奶牛 i 属于 G。"
      }
    ]
  },
  "status": "success"
}