{
  "problem_id": "CF1799C",
  "source": "codeforces",
  "input_structure": {
    "type": "array",
    "confidence": "1/1",
    "all_rounds": [
      {
        "round": 1,
        "status": "success",
        "result": {
          "type": "array",
          "length": {
            "min": 1,
            "max": 100000
          },
          "value_range": {
            "min": 97,
            "max": 122
          },
          "properties": {}
        }
      }
    ],
    "length": {
      "min": 1,
      "max": 100000
    },
    "value_range": {
      "min": 97,
      "max": 122
    },
    "properties": {}
  },
  "core_constraints": {
    "constraints": [
      {
        "name": "ordering",
        "description": "字符串的字典序最小化（通过重新排列字符）",
        "confidence": "1/1"
      },
      {
        "name": "alphabet_constraint",
        "description": "字符串仅由小写英文字母组成",
        "confidence": "1/1"
      }
    ],
    "all_rounds": [
      {
        "round": 1,
        "status": "success",
        "result": {
          "constraints": [
            {
              "name": "ordering",
              "description": "字符串的字典序最小化（通过重新排列字符）"
            },
            {
              "name": "ordering",
              "description": "字符串及其反转后的字典序最大值"
            },
            {
              "name": "alphabet_constraint",
              "description": "字符串仅由小写英文字母组成"
            }
          ]
        }
      }
    ]
  },
  "objective": {
    "type": "lexicographic_optimize",
    "confidence": "1/1",
    "all_rounds": [
      {
        "round": 1,
        "status": "success",
        "result": {
          "type": "lexicographic_optimize",
          "description": "求字符串重排后的字典序最小值"
        }
      }
    ],
    "description": "求字符串重排后的字典序最小值"
  },
  "invariant": {
    "invariants": [
      {
        "name": "optimal_substructure",
        "description": "最优解可以通过子问题的最优解构造，即通过确定每个字符的位置来构建最终字符串t，使得t_max最小。",
        "confidence": "1/1",
        "properties": {}
      },
      {
        "name": "greedy_choice",
        "description": "局部最优选择导致全局最优，即在每一步选择中，优先考虑将当前剩余字符中字典序最小的字符放置在合适位置以保证t_max最小。",
        "confidence": "1/1",
        "properties": {}
      }
    ],
    "all_rounds": [
      {
        "round": 1,
        "status": "success",
        "result": {
          "invariants": [
            {
              "name": "optimal_substructure",
              "description": "最优解可以通过子问题的最优解构造，即通过确定每个字符的位置来构建最终字符串t，使得t_max最小。",
              "properties": {}
            },
            {
              "name": "greedy_choice",
              "description": "局部最优选择导致全局最优，即在每一步选择中，优先考虑将当前剩余字符中字典序最小的字符放置在合适位置以保证t_max最小。",
              "properties": {}
            }
          ]
        }
      }
    ]
  }
}