{
  "problem_id": "CF558D",
  "source": "codeforces",
  "input_structure": {
    "type": "undirected_graph",
    "confidence": "1/1",
    "all_rounds": [
      {
        "round": 1,
        "status": "success",
        "result": {
          "type": "undirected_graph",
          "length": {
            "min": 1,
            "max": 50
          },
          "value_range": {
            "min": 1,
            "max": 1048575
          },
          "properties": {
            "connected": true,
            "binary": true
          }
        }
      }
    ],
    "length": {
      "min": 1,
      "max": 50
    },
    "value_range": {
      "min": 1,
      "max": 1048575
    },
    "properties": {
      "connected": true,
      "binary": true
    }
  },
  "core_constraints": {
    "constraints": [
      {
        "name": "lowest_common_ancestor_comparison",
        "description": "对于每个节点，可以查询其祖先节点是否在指定范围内",
        "confidence": "1/1"
      },
      {
        "name": "distinct_solution_constraint",
        "description": "根据所有查询结果，必须能够唯一确定一个解或判断信息矛盾",
        "confidence": "1/1"
      },
      {
        "name": "pairwise_exclusion",
        "description": "所有查询的答案不能相互矛盾",
        "confidence": "1/1"
      }
    ],
    "all_rounds": [
      {
        "round": 1,
        "status": "success",
        "result": {
          "constraints": [
            {
              "name": "lowest_common_ancestor_comparison",
              "description": "对于每个节点，可以查询其祖先节点是否在指定范围内"
            },
            {
              "name": "distinct_solution_constraint",
              "description": "根据所有查询结果，必须能够唯一确定一个解或判断信息矛盾"
            },
            {
              "name": "pairwise_exclusion",
              "description": "所有查询的答案不能相互矛盾"
            }
          ]
        }
      }
    ]
  },
  "objective": {
    "type": "maximize_count",
    "confidence": "1/1",
    "all_rounds": [
      {
        "round": 1,
        "status": "success",
        "result": {
          "type": "maximize_count",
          "description": "判断给定的条件是否一致，如果一致则进一步判断是否存在唯一解"
        }
      }
    ],
    "description": "判断给定的条件是否一致，如果一致则进一步判断是否存在唯一解"
  },
  "invariant": {
    "name": "optimal_substructure",
    "confidence": "1/1",
    "all_rounds": [
      {
        "round": 1,
        "status": "success",
        "result": {
          "name": "optimal_substructure",
          "description": "最优子结构：解空间的合法性由子问题的解组合而成，通过递归或迭代方式逐步缩小问题规模直至找到唯一解或确定无解。",
          "properties": {
            "subproblem_independence": true,
            "solution_combinability": true
          }
        }
      }
    ],
    "description": "最优子结构：解空间的合法性由子问题的解组合而成，通过递归或迭代方式逐步缩小问题规模直至找到唯一解或确定无解。"
  }
}