{
  "problem_id": "CF877D",
  "source": "codeforces",
  "input_structure": {
    "type": "matrix",
    "confidence": "1/1",
    "all_rounds": [
      {
        "round": 1,
        "status": "success",
        "result": {
          "type": "matrix",
          "length": {
            "min": 1,
            "max": 1000
          },
          "value_range": {
            "min": 0,
            "max": 1
          },
          "properties": {
            "connected": false
          }
        }
      }
    ],
    "length": {
      "min": 1,
      "max": 1000
    },
    "value_range": {
      "min": 0,
      "max": 1
    },
    "properties": {
      "connected": false
    }
  },
  "core_constraints": {
    "constraints": [
      {
        "name": "edge_exclusion_constraint",
        "description": "路径不能经过障碍物（图中某些节点不可达）",
        "confidence": "1/1"
      },
      {
        "name": "path_length_constraint",
        "description": "每次移动的距离在 1 到 k 之间（步长约束）",
        "confidence": "1/1"
      },
      {
        "name": "orientation_constraint",
        "description": "只能向四个方向之一移动（上下左右）",
        "confidence": "1/1"
      },
      {
        "name": "source_node_fixed",
        "description": "起点和终点必须是空的（起点和终点可达且为空）",
        "confidence": "1/1"
      }
    ],
    "all_rounds": [
      {
        "round": 1,
        "status": "success",
        "result": {
          "constraints": [
            {
              "name": "edge_exclusion_constraint",
              "description": "路径不能经过障碍物（图中某些节点不可达）"
            },
            {
              "name": "path_length_constraint",
              "description": "每次移动的距离在 1 到 k 之间（步长约束）",
              "formal": "1 ≤ d ≤ k"
            },
            {
              "name": "orientation_constraint",
              "description": "只能向四个方向之一移动（上下左右）"
            },
            {
              "name": "source_node_fixed",
              "description": "起点和终点必须是空的（起点和终点可达且为空）"
            }
          ]
        }
      }
    ]
  },
  "objective": {
    "type": "minimize_distance",
    "confidence": "1/1",
    "all_rounds": [
      {
        "round": 1,
        "status": "success",
        "result": {
          "type": "minimize_distance",
          "description": "求两点间最短路径长度"
        }
      }
    ],
    "description": "求两点间最短路径长度"
  },
  "invariant": {
    "name": "optimal_substructure",
    "confidence": "1/1",
    "all_rounds": [
      {
        "round": 1,
        "status": "success",
        "result": {
          "name": "optimal_substructure",
          "description": "最优子结构：从起点到终点的最短路径可以通过子路径的最优解组合而成，满足DAG上的最优子结构",
          "properties": {}
        }
      }
    ],
    "description": "最优子结构：从起点到终点的最短路径可以通过子路径的最优解组合而成，满足DAG上的最优子结构"
  }
}