{
  "problem_id": "GYM106035C",
  "source": "icpc_gym",
  "input_structure": {
    "type": "matrix",
    "confidence": "1/1",
    "all_rounds": [
      {
        "round": 1,
        "status": "success",
        "result": {
          "type": "matrix",
          "length": {
            "min": 3,
            "max": 3
          },
          "value_range": {
            "min": 0,
            "max": 1000000000
          },
          "properties": {
            "ordered": false
          }
        }
      }
    ],
    "length": {
      "min": 3,
      "max": 3
    },
    "value_range": {
      "min": 0,
      "max": 1000000000
    },
    "properties": {
      "ordered": false
    }
  },
  "core_constraints": {
    "constraints": [
      {
        "name": "popcount_constraint",
        "description": "计算给定表达式的二进制表示中1的数量",
        "confidence": "1/1"
      }
    ],
    "all_rounds": [
      {
        "round": 1,
        "status": "success",
        "result": {
          "constraints": [
            {
              "name": "popcount_constraint",
              "description": "计算给定表达式的二进制表示中1的数量",
              "formal": "count_ones((2^n + 2^m)^k)"
            }
          ]
        }
      }
    ]
  },
  "objective": {
    "type": "maximize_count",
    "confidence": "1/1",
    "all_rounds": [
      {
        "round": 1,
        "status": "success",
        "result": {
          "type": "maximize_count",
          "description": "计算给定数值的二进制表示中1的数量"
        }
      }
    ],
    "description": "计算给定数值的二进制表示中1的数量"
  },
  "invariant": {
    "name": "optimal_substructure",
    "confidence": "1/1",
    "all_rounds": [
      {
        "round": 1,
        "status": "success",
        "result": {
          "name": "optimal_substructure",
          "description": "最优子结构：问题的解可以通过子问题的解组合而成，具体表现为通过计算较小幂次的结果来推导较大幂次的结果。",
          "properties": {}
        }
      }
    ],
    "description": "最优子结构：问题的解可以通过子问题的解组合而成，具体表现为通过计算较小幂次的结果来推导较大幂次的结果。"
  }
}