{
  "problem_id": "GYM105633J",
  "source": "icpc_gym",
  "input_structure": {
    "type": "matrix",
    "confidence": "1/1",
    "all_rounds": [
      {
        "round": 1,
        "status": "success",
        "result": {
          "type": "matrix",
          "length": {
            "min": 1,
            "max": 1000
          },
          "value_range": {
            "min": 1,
            "max": 100000
          },
          "properties": {
            "inferred": true
          }
        }
      }
    ],
    "length": {
      "min": 1,
      "max": 1000
    },
    "value_range": {
      "min": 1,
      "max": 100000
    },
    "properties": {
      "inferred": true
    }
  },
  "core_constraints": {
    "constraints": [
      {
        "name": "total_sum_constraint",
        "description": "选取元素的权重和必须等于预定总重量",
        "confidence": "1/1"
      },
      {
        "name": "interval_constraint",
        "description": "每个元素的实际值在给定范围内",
        "confidence": "1/1"
      },
      {
        "name": "minimum_error_constraint",
        "description": "最小化最大误差，即实际值与目标值的最大绝对差",
        "confidence": "1/1"
      }
    ],
    "all_rounds": [
      {
        "round": 1,
        "status": "success",
        "result": {
          "constraints": [
            {
              "name": "total_sum_constraint",
              "description": "选取元素的权重和必须等于预定总重量",
              "formal": "sum(a_i * x_i) = s, 其中 0 <= x_i <= 1"
            },
            {
              "name": "interval_constraint",
              "description": "每个元素的实际值在给定范围内",
              "formal": "l_i / M * a_i <= y_i <= r_i / M * a_i, 其中 y_i 是第 i 个元素的实际值"
            },
            {
              "name": "minimum_error_constraint",
              "description": "最小化最大误差，即实际值与目标值的最大绝对差",
              "formal": "minimize(max(|y_a - y_t|)), 其中 y_a 在 [sum(l_i * x_i), sum(r_i * x_i)] 范围内"
            }
          ]
        }
      }
    ]
  },
  "objective": {
    "type": "minimize_cost",
    "confidence": "1/1",
    "all_rounds": [
      {
        "round": 1,
        "status": "success",
        "result": {
          "type": "minimize_cost",
          "description": "求最小化最大误差值"
        }
      }
    ],
    "description": "求最小化最大误差值"
  },
  "invariant": {
    "name": "optimal_substructure",
    "confidence": "1/1",
    "all_rounds": [
      {
        "round": 1,
        "status": "success",
        "result": {
          "name": "optimal_substructure",
          "description": "最优子结构：问题的最优解可以通过子问题的最优解组合而成，每个子问题的解是独立且最优的",
          "properties": {}
        }
      }
    ],
    "description": "最优子结构：问题的最优解可以通过子问题的最优解组合而成，每个子问题的解是独立且最优的"
  }
}