{
  "problem_id": "P4212",
  "source": "luogu",
  "input_structure": {
    "type": "undirected_graph",
    "confidence": "1/1",
    "all_rounds": [
      {
        "round": 1,
        "status": "success",
        "result": {
          "type": "undirected_graph",
          "length": {
            "min": 1,
            "max": 50
          },
          "value_range": {
            "min": 1,
            "max": 50
          },
          "properties": {
            "connected": false,
            "weighted": false
          }
        }
      }
    ],
    "length": {
      "min": 1,
      "max": 50
    },
    "value_range": {
      "min": 1,
      "max": 50
    },
    "properties": {
      "connected": false,
      "weighted": false
    }
  },
  "core_constraints": {
    "constraints": [
      {
        "name": "complete_subgraph",
        "description": "选取的节点必须形成一个完全子图（即所有选中的节点之间都是朋友关系）",
        "confidence": "1/1"
      },
      {
        "name": "pairwise_exclusion",
        "description": "任意两个未被选中的节点之间不能是朋友关系（即敌人关系）",
        "confidence": "1/1"
      }
    ],
    "all_rounds": [
      {
        "round": 1,
        "status": "success",
        "result": {
          "constraints": [
            {
              "name": "complete_subgraph",
              "description": "选取的节点必须形成一个完全子图（即所有选中的节点之间都是朋友关系）"
            },
            {
              "name": "pairwise_exclusion",
              "description": "任意两个未被选中的节点之间不能是朋友关系（即敌人关系）"
            }
          ]
        }
      }
    ]
  },
  "objective": {
    "type": "maximize_value",
    "confidence": "1/1",
    "all_rounds": [
      {
        "round": 1,
        "status": "success",
        "result": {
          "type": "maximize_value",
          "description": "求满足条件的最大集合大小"
        }
      }
    ],
    "description": "求满足条件的最大集合大小"
  },
  "invariant": {
    "name": "optimal_substructure",
    "confidence": "1/1",
    "all_rounds": [
      {
        "round": 1,
        "status": "success",
        "result": {
          "name": "optimal_substructure",
          "description": "最优子结构：问题的最优解可以通过子问题的最优解组合而成，即最大独立集问题可以通过求解子图的最大独立集来解决",
          "properties": {}
        }
      }
    ],
    "description": "最优子结构：问题的最优解可以通过子问题的最优解组合而成，即最大独立集问题可以通过求解子图的最大独立集来解决"
  }
}