{
  "problem_id": "P6299",
  "source": "luogu",
  "input_structure": {
    "type": "array",
    "confidence": "1/1",
    "all_rounds": [
      {
        "round": 1,
        "status": "success",
        "result": {
          "type": "array",
          "length": {
            "min": 4,
            "max": 4
          },
          "value_range": {
            "min": -1000000000,
            "max": 1000000000
          },
          "properties": {}
        }
      }
    ],
    "length": {
      "min": 4,
      "max": 4
    },
    "value_range": {
      "min": -1000000000,
      "max": 1000000000
    },
    "properties": {}
  },
  "core_constraints": {
    "constraints": [
      {
        "name": "minimum_value_constraint",
        "description": "求解目标函数的非零最小值",
        "confidence": "1/1"
      },
      {
        "name": "optimization_objective",
        "description": "解的绝对值必须小于 2^63",
        "confidence": "1/1"
      },
      {
        "name": "pairwise_difference_constraint",
        "description": "当 a=1, b=9, c=2, d=6 时，差别度 M 必须为偶数",
        "confidence": "1/1"
      }
    ],
    "all_rounds": [
      {
        "round": 1,
        "status": "success",
        "result": {
          "constraints": [
            {
              "name": "minimum_value_constraint",
              "description": "求解目标函数的非零最小值",
              "formal": "M > 0 且 M 最小"
            },
            {
              "name": "optimization_objective",
              "description": "解的绝对值必须小于 2^63",
              "formal": "|p|, |q|, |r|, |s|, |M| < 2^63"
            },
            {
              "name": "pairwise_difference_constraint",
              "description": "当 a=1, b=9, c=2, d=6 时，差别度 M 必须为偶数",
              "formal": "a=1, b=9, c=2, d=6 => M % 2 == 0"
            }
          ]
        }
      }
    ]
  },
  "objective": {
    "type": "minimize_value",
    "confidence": "1/1",
    "all_rounds": [
      {
        "round": 1,
        "status": "success",
        "result": {
          "type": "minimize_value",
          "description": "求给定表达式的非零最小值"
        }
      }
    ],
    "description": "求给定表达式的非零最小值"
  },
  "invariant": {
    "invariants": [
      {
        "name": "optimal_substructure",
        "description": "最优子结构：差别度 M 的非零最小值可以通过分解为更小的子问题来求解，每个子问题的最优解组合成全局最优解。",
        "confidence": "1/1",
        "properties": {}
      },
      {
        "name": "symmetry",
        "description": "对称性：在某些情况下，通过交换或变换变量 p, q, r, s 可以得到相同的差别度 M，这种对称性可以简化搜索空间。",
        "confidence": "1/1",
        "properties": {}
      }
    ],
    "all_rounds": [
      {
        "round": 1,
        "status": "success",
        "result": {
          "invariants": [
            {
              "name": "optimal_substructure",
              "description": "最优子结构：差别度 M 的非零最小值可以通过分解为更小的子问题来求解，每个子问题的最优解组合成全局最优解。",
              "properties": {}
            },
            {
              "name": "symmetry",
              "description": "对称性：在某些情况下，通过交换或变换变量 p, q, r, s 可以得到相同的差别度 M，这种对称性可以简化搜索空间。",
              "properties": {}
            }
          ]
        }
      }
    ]
  }
}