{
  "problem_id": "CF1481D",
  "source": "codeforces",
  "input_structure": [
    {
      "round": 1,
      "status": "success",
      "result": {
        "type": "directed_graph",
        "length": {
          "min": 2,
          "max": 1000
        },
        "value_range": {
          "min": 1,
          "max": 100000
        },
        "properties": {
          "connected": true,
          "weighted": false,
          "directed": true
        }
      }
    }
  ],
  "core_constraints": [
    {
      "round": 1,
      "status": "success",
      "result": {
        "constraints": [
          {
            "name": "palindrome",
            "description": "路径上的边标签构成的字符串必须是回文串"
          },
          {
            "name": "distance_bound",
            "description": "路径长度必须为给定的 m"
          },
          {
            "name": "acyclicity",
            "description": "图是一个完全有向图，每对不同的顶点之间都有两条方向相反的边"
          },
          {
            "name": "labeling_constraint",
            "description": "每条有向边被标记为 'a' 或 'b'，且两个方向的边可以有不同的标签"
          },
          {
            "name": "revisiting_allowed",
            "description": "可以多次访问同一个顶点和同一条有向边"
          }
        ]
      }
    }
  ],
  "objective": [
    {
      "round": 1,
      "status": "success",
      "result": {
        "type": "feasibility",
        "description": "判断是否存在长度为m的路径，使得路径上的边标签构成回文串"
      }
    }
  ],
  "invariant": [
    {
      "round": 1,
      "status": "success",
      "result": {
        "invariants": [
          {
            "name": "symmetry",
            "description": "对称性：路径上的字符序列与其逆序相同，满足回文性质",
            "properties": {}
          },
          {
            "name": "subproblem_independence",
            "description": "子问题独立性：每个子路径的回文性质独立于其他子路径，可以分别处理",
            "properties": {}
          }
        ]
      }
    }
  ]
}