{
  "problem_id": "CF1598D",
  "source": "codeforces",
  "input_structure": [
    {
      "round": 1,
      "status": "success",
      "result": {
        "type": "array",
        "length": {
          "min": 3,
          "max": 200000
        },
        "value_range": {
          "min": 1,
          "max": 200000
        },
        "properties": {
          "unique_pairs": true
        }
      }
    }
  ],
  "core_constraints": [
    {
      "round": 1,
      "status": "success",
      "result": {
        "constraints": [
          {
            "name": "distinctness",
            "description": "所有问题的 (主题, 难度) 对必须唯一"
          },
          {
            "name": "subset_constraint",
            "description": "从 n 个问题中选择恰好 3 个问题"
          }
        ]
      }
    }
  ],
  "objective": [
    {
      "round": 1,
      "status": "success",
      "result": {
        "type": "enumeration",
        "description": "求满足条件的三元组数量"
      }
    }
  ],
  "invariant": [
    {
      "round": 1,
      "status": "success",
      "result": {
        "invariants": [
          {
            "name": "optimal_substructure",
            "description": "最优子结构：选择三个问题的方案数可以通过子问题的解来计算，即通过组合不同的话题和难度来确定满足条件的三元组数量。",
            "properties": {}
          },
          {
            "name": "subproblem_independence",
            "description": "子问题独立性：每个子问题（选择特定话题和难度的问题）的解是独立的，可以分别计算后再进行组合。",
            "properties": {}
          }
        ]
      }
    }
  ]
}