{
  "problem_id": "GYM104666L",
  "source": "icpc_gym",
  "input_structure": [
    {
      "round": 1,
      "status": "success",
      "result": {
        "type": "matrix",
        "length": {
          "min": 3,
          "max": 200000
        },
        "value_range": {
          "min": 1,
          "max": 1000000000
        },
        "properties": {}
      }
    }
  ],
  "core_constraints": [
    {
      "round": 1,
      "status": "success",
      "result": {
        "constraints": [
          {
            "name": "triple_sum_constraint",
            "description": "分析序列中的所有三元组，这些三元组是序列的子序列，即三元组中的元素在原序列中按相同顺序出现，但不一定连续。",
            "formal": "对于序列 A，找到所有 (i, j, k) 使得 i < j < k 且 A[i], A[j], A[k] 是一个三元组"
          },
          {
            "name": "distinct_vertex_colorings",
            "description": "三元组根据其标签进行分组，需要输出所有不同的三元组标签，并按字典序排序。",
            "formal": "对于每个三元组 (A[i], A[j], A[k])，生成标签 L = (A[i], A[j], A[k]) 并去重后按字典序输出"
          }
        ]
      }
    }
  ],
  "objective": [
    {
      "round": 1,
      "status": "success",
      "result": {
        "type": "maximize_count",
        "description": "统计所有不同的三元组标签数量"
      }
    }
  ],
  "invariant": [
    {
      "round": 1,
      "status": "success",
      "result": {
        "name": "optimal_substructure",
        "description": "最优子结构：大问题的解由子问题的解组合而成，通过分析所有可能的三元组来确定最终结果",
        "properties": {}
      }
    }
  ]
}