{
  "problem_id": "GYM106185I",
  "source": "icpc_gym",
  "input_structure": [
    {
      "round": 1,
      "status": "success",
      "result": {
        "type": "array",
        "length": {
          "min": 4,
          "max": 400000
        },
        "value_range": {
          "min": 1,
          "max": 200000
        },
        "properties": {
          "ordered": false
        }
      }
    }
  ],
  "core_constraints": [
    {
      "round": 1,
      "status": "success",
      "result": {
        "constraints": [
          {
            "name": "matching_constraint",
            "description": "每对相对位置的节点必须具有相同的值（匹配约束）"
          },
          {
            "name": "frequency_bound",
            "description": "每个值的出现次数为偶数（频次约束）"
          },
          {
            "name": "operation_type",
            "description": "只能通过交换相邻节点的值来重新排列（操作类型限制）"
          }
        ]
      }
    }
  ],
  "objective": [
    {
      "round": 1,
      "status": "success",
      "result": {
        "type": "minimize_value",
        "description": "求最小化交换次数以满足特定条件"
      }
    }
  ],
  "invariant": [
    {
      "round": 1,
      "status": "success",
      "result": {
        "invariants": [
          {
            "name": "symmetry",
            "description": "对称性：对于任意一对相对位置的学生，其午餐盒类型在交换操作后仍保持对称关系不变",
            "properties": {}
          },
          {
            "name": "exchange_argument",
            "description": "交换论证：通过局部交换相邻学生午餐盒的操作，可以逐步减少不满足条件的相对位置对数，直至所有相对位置对均满足条件",
            "properties": {}
          }
        ]
      }
    }
  ]
}