{
  "problem_id": "P13973",
  "source": "luogu",
  "input_structure": [
    {
      "round": 1,
      "status": "success",
      "result": {
        "type": "matrix",
        "length": {
          "min": 1,
          "max": 300000
        },
        "value_range": {
          "min": 1,
          "max": 300000
        },
        "properties": {
          "distinct": true
        }
      }
    }
  ],
  "core_constraints": [
    {
      "round": 1,
      "status": "success",
      "result": {
        "constraints": [
          {
            "name": "distinct_elements",
            "description": "数组中的所有元素互不相同"
          },
          {
            "name": "minimum_maximum_constraint",
            "description": "对于每个子数组，计算其最大值与最小值的整数除法结果，并求这些结果的总和"
          }
        ]
      }
    }
  ],
  "objective": [
    {
      "round": 1,
      "status": "success",
      "result": {
        "type": "maximize_sum_of_squares",
        "description": "求所有子数组中最大值与最小值整除结果的和"
      }
    }
  ],
  "invariant": [
    {
      "round": 1,
      "status": "success",
      "result": {
        "name": "interval_mergeable",
        "description": "区间可合并性：子区间的最大值和最小值可通过端点信息计算，从而实现区间结果的高效合并",
        "properties": {
          "prefix_sum": false,
          "segment_tree": true
        }
      }
    }
  ]
}